catswalk/__init__.py
catswalk/scraping/__init__.py
catswalk/scraping/async_request.py
catswalk/scraping/request.py
catswalk/scraping/webdriver.py
catswalk/scraping/driverfunc/__init__.py
catswalk/scraping/driverfunc/jquery.py
catswalk/scraping/driverfunc/wait.py
catswalk/scraping/types/__init__.py
catswalk/scraping/types/type_response.py
catswalk/scraping/types/type_webdriver.py
catswalk/utils/__init__.py
catswalk/utils/functional.py
tests/__init__.py
tests/test_aio_request.py
tests/test_printscreen.py
tests/test_scroll.py
tests/scraping/__init__.py
tests/scraping/test_async_request.py
tests/scraping/test_request.py
tests/scraping/test_web_driver.py
catswalk-0.2.9.dist-info/METADATA
catswalk-0.2.9.dist-info/WHEEL
catswalk-0.2.9.dist-info/top_level.txt
catswalk-0.2.9.dist-info/RECORD
