Metadata-Version: 2.1
Name: catswalk
Version: 0.2.9
Summary: Core library for crawling and web scraping
Home-page: https://rescala.jp
Author: rv
Author-email: yo-maruya@rescala.jp
License: MIT
Project-URL: Bug Reports, https://github.com/rv-rescala/catsrequest/issues
Project-URL: Source, https://github.com/rv-rescala/catsrequest
Keywords: python crawler scraping
Platform: UNKNOWN
Requires-Python: >=3.7
Requires-Dist: requests
Requires-Dist: bs4
Requires-Dist: selenium (==3.141.0)
Requires-Dist: lxml
Requires-Dist: emoji
Requires-Dist: pysocks
Requires-Dist: aiohttp
Requires-Dist: pillow
